async_responses/__init__.py
async_responses/async_responses.py
async_responses-1.0.0.dist-info/LICENSE
async_responses-1.0.0.dist-info/WHEEL
async_responses-1.0.0.dist-info/METADATA
async_responses-1.0.0.dist-info/RECORD
