Metadata-Version: 2.1
Name: async-responses
Version: 1.0.0
Summary: aiohttp testing library
Home-page: https://ulam.io/
License: MIT
Keywords: aiohttp,testing
Author: Sławomir Górawski
Author-email: slawomir@ulam.io
Requires-Python: >=3.7,<4.0
Classifier: License :: OSI Approved :: MIT License
Classifier: Programming Language :: Python :: 3
Classifier: Programming Language :: Python :: 3.7
Classifier: Programming Language :: Python :: 3.8
Requires-Dist: aiohttp (>=3.3.1)
Project-URL: Documentation, https://async-responses.readthedocs.io/en/latest/
Project-URL: Repository, https://github.com/ulamlabs/async-responses
